rapid_kit/__init__.py
rapid_kit/auth.py
rapid_kit/capture.py
rapid_kit/chat_channel.py
rapid_kit/debug.py
rapid_kit/http.py
rapid_kit/initialize.py
rapid_kit/instruct.py
rapid_kit/lan.py
rapid_kit/lib.py
rapid_kit/log.py
rapid_kit/media_chat.py
rapid_kit/packet.py
rapid_kit/persistent_channel.py
rapid_kit/pipe.py
rapid_kit/player.py
rapid_kit/profile.py
rapid_kit/sdl.py
rapid_kit/signal.py
rapid_kit/stats.py
rapid_kit/stream.py
rapid_kit/unauthorized.py
rapid_kit-1.3.0.dist-info/licenses/LICENSE
rapid_kit-1.3.0.dist-info/METADATA
rapid_kit-1.3.0.dist-info/WHEEL
rapid_kit-1.3.0.dist-info/top_level.txt
rapid_kit-1.3.0.dist-info/RECORD
